<annotation>
	<folder>jpgimages</folder>
	<filename>171.jpg</filename>
	<path>/jpgimages/171.jpg</path>
	<source>
		<database>Unspecified</database>
	</source>
	<size>
		<width>3806</width>
		<height>4757</height>
		<depth>3</depth>
	</size>
	<object>
		<name>excavator</name>
		<pose>Unspecified</pose>
		<truncated>Unspecified</truncated>
		<difficult>Unspecified</difficult>
		<bndbox>
			<xmin>55</xmin>
			<ymin>2130</ymin>
			<xmax>3253</xmax>
			<ymax>3846</ymax>
		</bndbox>
	</object>
</annotation>